modules/__init__.py
modules/ai_client.py
modules/colors.py
modules/config.py
modules/telegram_bot.py
modules/utils.py
neurax/__init__.py
neurax/ai_client.py
neurax/cli.py
neurax/colors.py
neurax/config.py
neurax/telegram_bot.py
neurax/utils.py
neurax_ai-1.0.0.dist-info/licenses/LICENSE
neurax_ai-1.0.0.dist-info/METADATA
neurax_ai-1.0.0.dist-info/WHEEL
neurax_ai-1.0.0.dist-info/entry_points.txt
neurax_ai-1.0.0.dist-info/top_level.txt
neurax_ai-1.0.0.dist-info/RECORD
