Metadata-Version: 2.4
Name: neurax-ai
Version: 1.0.0
Summary: A powerful CLI and Telegram bot interface for Perplexity AI
Home-page: https://github.com/VritraSecz/NeuraX
Author: Alex Butler
Project-URL: Bug Tracker, https://github.com/VritraSecz/NeuraX/issues
Project-URL: Documentation, https://github.com/VritraSecz/NeuraX/blob/main/README.md
Project-URL: Source Code, https://github.com/VritraSecz/NeuraX
Project-URL: Developer Website, https://vritrasec.com
Project-URL: Telegram Channel, https://t.me/VritraSec
Keywords: ai,chatbot,telegram,cli,perplexity,assistant,neurax
Classifier: Development Status :: 5 - Production/Stable
Classifier: Intended Audience :: Developers
Classifier: Intended Audience :: System Administrators
Classifier: License :: OSI Approved :: MIT License
Classifier: Operating System :: OS Independent
Classifier: Programming Language :: Python :: 3
Classifier: Programming Language :: Python :: 3.7
Classifier: Programming Language :: Python :: 3.8
Classifier: Programming Language :: Python :: 3.9
Classifier: Programming Language :: Python :: 3.10
Classifier: Programming Language :: Python :: 3.11
Classifier: Programming Language :: Python :: 3.12
Classifier: Topic :: Communications :: Chat
Classifier: Topic :: Scientific/Engineering :: Artificial Intelligence
Classifier: Topic :: Software Development :: Libraries :: Python Modules
Classifier: Topic :: Utilities
Requires-Python: >=3.7
License-File: LICENSE
Requires-Dist: requests>=2.31.0
Requires-Dist: python-telegram-bot==21.5
Requires-Dist: pytz>=2024.1
Requires-Dist: colorama>=0.4.6
Dynamic: author
Dynamic: classifier
Dynamic: description
Dynamic: description-content-type
Dynamic: home-page
Dynamic: keywords
Dynamic: license-file
Dynamic: project-url
Dynamic: requires-dist
Dynamic: requires-python
Dynamic: summary
